{
  "title": "NESA's Workshop in Chechnya",
  "date": "December 16 2016",
  "image": "/blog/Chechnya07.jpg",
  "gallery": [{
      "caption": "image",
      "url": "/blog/Chechnya01.jpg"
    },
    {
      "caption": "image",
      "url": "/blog/Chechnya02.jpg"
    }, {
      "caption": "image",
      "url": "/blog/Chechnya03.jpg"
    }, {
      "caption": "image",
      "url": "/blog/Chechnya04.jpg"
    }, {
      "caption": "image",
      "url": "/blog/Chechnya05.jpg"
    }, {
      "caption": "image",
      "url": "/blog/Chechnya06.jpg"
    }, {
      "caption": "image",
      "url": "/blog/Chechnya07.jpg"
    }, {
      "caption": "image",
      "url": "/blog/Chechnya08.jpg"
    }, {
      "caption": "image",
      "url": "/blog/Chechnya09.jpg"
    }, {
      "caption": "image",
      "url": "/blog/Chechnya10.jpg"
    }
  ],
  "body": "The NESA conducted a surgical workshop in Grozny and Gudermes, Chechnya from December 13-16 with NESA members from Germany, Israel, Russia and Turkey. In each city, live surgeries were performed. \n\n The workshop was well attended by 700 participants and was opened with the participation of the Chechen Health Minister. \n\n The workshop was followed in the local and Russian television networks. Following this workshop, the NESA has already been invited for future workshops in other Republics and in Moscow "
}
